mcp_hitchcode/__init__.py
mcp_hitchcode/__main__.py
mcp_hitchcode/server.py
mcp_hitchcode/templates/__init__.py
mcp_hitchcode/templates/docker_file_loader.py
mcp_hitchcode/templates/template_loader.py
mseep_mcp_hitchcode-0.1.3.dist-info/licenses/LICENSE
mseep_mcp_hitchcode-0.1.3.dist-info/METADATA
mseep_mcp_hitchcode-0.1.3.dist-info/WHEEL
mseep_mcp_hitchcode-0.1.3.dist-info/top_level.txt
mseep_mcp_hitchcode-0.1.3.dist-info/RECORD
