Metadata-Version: 2.4
Name: mseep-mcp-hitchcode
Version: 0.1.3
Summary: An MCP server providing tools for applying code templates and facilitating structured vibe coding assistance
Home-page: 
Author: mseep
Author-email: support@skydeck.ai
Maintainer: mseep
Maintainer-email: support@skydeck.ai
Keywords: mseep,mcp,llm,automation,web,fetch,code-templates,vibe-coding
Classifier: Programming Language :: Python :: 3
Classifier: License :: OSI Approved :: MIT License
Classifier: Operating System :: OS Independent
Requires-Python: >=3.6
License-File: LICENSE
Requires-Dist: anyio>=4.5
Requires-Dist: beautifulsoup4>=4.13.3
Requires-Dist: click>=8.1.0
Requires-Dist: httpx>=0.27
Requires-Dist: jinja2>=3.1.5
Requires-Dist: mcp
Requires-Dist: packaging>=24.2
Requires-Dist: pytest>=8.3.4
Requires-Dist: pyyaml>=6.0.2
Dynamic: author
Dynamic: author-email
Dynamic: classifier
Dynamic: description
Dynamic: description-content-type
Dynamic: keywords
Dynamic: license-file
Dynamic: maintainer
Dynamic: maintainer-email
Dynamic: requires-dist
Dynamic: requires-python
Dynamic: summary
